Metadata-Version: 1.0
Name: ij-distributions
Version: 0.1
Summary: Gaussian and Binomial distributions
Home-page: UNKNOWN
Author: Ijeoma Ndu
Author-email: ijeendu@gmail.com
License: UNKNOWN
Platform: UNKNOWN
